fast_json_to_csv/fast_json_to_csv/__init__.py
fast_json_to_csv/fast_json_to_csv/converter.py
fast_json_to_csv/tests/__init__.py
fast_json_to_csv/tests/test_converter.py
fast_json_to_csv-0.1.0.dist-info/METADATA
fast_json_to_csv-0.1.0.dist-info/WHEEL
fast_json_to_csv-0.1.0.dist-info/licenses/LICENSE
fast_json_to_csv-0.1.0.dist-info/RECORD
