Metadata-Version: 2.4
Name: fast-json-to-csv
Version: 0.1.0
Summary: A fast and efficient JSON to CSV converter
Project-URL: Homepage, https://github.com/mariyasnow/fast-json-to-csv
Project-URL: Bug Tracker, https://github.com/mariyasnow/fast-json-to-csv/issues
Author-email: Maria Snow <mariyasnow@github.com>
License-File: LICENSE
Classifier: Development Status :: 4 - Beta
Classifier: Intended Audience :: Developers
Classifier: License :: OSI Approved :: MIT License
Classifier: Operating System :: OS Independent
Classifier: Programming Language :: Python :: 3
Classifier: Programming Language :: Python :: 3.6
Classifier: Programming Language :: Python :: 3.7
Classifier: Programming Language :: Python :: 3.8
Classifier: Programming Language :: Python :: 3.9
Classifier: Programming Language :: Python :: 3.10
Classifier: Programming Language :: Python :: 3.11
Classifier: Topic :: Software Development :: Libraries :: Python Modules
Requires-Python: >=3.6
